wireprobe/__init__.py
wireprobe/fabfile.py
wireprobe/settings.yml.example
wireprobe/app/HealthCheck.py
wireprobe/app/__init__.py
wireprobe/app/Config/Config.py
wireprobe/app/Config/__init__.py
wireprobe/app/Notifications/Telegram.py
wireprobe/app/Notifications/__init__.py
wireprobe-0.2.dist-info/LICENSE
wireprobe-0.2.dist-info/METADATA
wireprobe-0.2.dist-info/WHEEL
wireprobe-0.2.dist-info/top_level.txt
wireprobe-0.2.dist-info/RECORD
