Metadata-Version: 2.1
Name: wireprobe
Version: 0.2
Summary: A wireguard app
Home-page: https://github.com/OpenPrunus/wireprobe/
Author: Benjamin Gounine
Author-email: prunus@ecuri.es
Requires-Python: >3.9
License-File: LICENSE
Requires-Dist: decorator
Requires-Dist: fabric
Requires-Dist: invoke
Requires-Dist: pyyaml
Requires-Dist: urllib3
